{"earnings": [{"actual": -0.27, "estimate": -0.1729, "period": "2025-12-31", "quarter": 4, "surprise": -0.0971, "surprisePercent": -56.1596, "symbol": "OKLO", "year": 2025}, {"actual": -0.2, "estimate": -0.1339, "period": "2025-09-30", "quarter": 3, "surprise": -0.0661, "surprisePercent": -49.3652, "symbol": "OKLO", "year": 2025}, {"actual": -0.18, "estimate": -0.1118, "period": "2025-06-30", "quarter": 2, "surprise": -0.0682, "surprisePercent": -61.0018, "symbol": "OKLO", "year": 2025}, {"actual": -0.07, "estimate": -0.1107, "period": "2025-03-31", "quarter": 1, "surprise": 0.0407, "surprisePercent": 36.766, "symbol": "OKLO", "year": 2025}], "calendar": []}